CHANGELOG.txt
LICENCE.txt
MANIFEST.in
README.md
setup.py
morse_code/__init__.py
morse_code.egg-info/PKG-INFO
morse_code.egg-info/SOURCES.txt
morse_code.egg-info/dependency_links.txt
morse_code.egg-info/top_level.txt